[
  {
    "mode": "NULLABLE",
    "name": "name",
    "type": "STRING"
  },
  {
    "mode": "NULLABLE",
    "name": "assetType",
    "type": "STRING"
  },
  {
    "fields": [
      {
        "mode": "NULLABLE",
        "name": "version",
        "type": "STRING"
      },
      {
        "mode": "NULLABLE",
        "name": "discoveryDocumentUri",
        "type": "STRING"
      },
      {
        "mode": "NULLABLE",
        "name": "discoveryName",
        "type": "STRING"
      },
      {
        "mode": "NULLABLE",
        "name": "resourceUrl",
        "type": "STRING"
      },
      {
        "mode": "NULLABLE",
        "name": "parent",
        "type": "STRING"
      },
      {
        "fields": [
          {
            "mode": "NULLABLE",
            "name": "kind",
            "type": "STRING"
          },
          {
            "mode": "NULLABLE",
            "name": "id",
            "type": "STRING"
          },
          {
            "mode": "NULLABLE",
            "name": "creationTimestamp",
            "type": "STRING"
          },
          {
            "mode": "NULLABLE",
            "name": "name",
            "type": "STRING"
          },
          {
            "mode": "NULLABLE",
            "name": "description",
            "type": "STRING"
          },
          {
            "mode": "NULLABLE",
            "name": "selfLink",
            "type": "STRING"
          },
          {
            "fields": [
              {
                "mode": "NULLABLE",
                "name": "description",
                "type": "STRING"
              },
              {
                "mode": "REPEATED",
                "name": "hosts",
                "type": "STRING"
              },
              {
                "mode": "NULLABLE",
                "name": "pathMatcher",
                "type": "STRING"
              }
            ],
            "mode": "REPEATED",
            "name": "hostRules",
            "type": "RECORD"
          },
          {
            "fields": [
              {
                "mode": "NULLABLE",
                "name": "name",
                "type": "STRING"
              },
              {
                "mode": "NULLABLE",
                "name": "description",
                "type": "STRING"
              },
              {
                "mode": "NULLABLE",
                "name": "defaultService",
                "type": "STRING"
              },
              {
                "fields": [
                  {
                    "fields": [
                      {
                        "mode": "NULLABLE",
                        "name": "backendService",
                        "type": "STRING"
                      },
                      {
                        "mode": "NULLABLE",
                        "name": "weight",
                        "type": "INTEGER"
                      },
                      {
                        "fields": [
                          {
                            "mode": "REPEATED",
                            "name": "requestHeadersToRemove",
                            "type": "STRING"
                          },
                          {
                            "fields": [
                              {
                                "mode": "NULLABLE",
                                "name": "headerName",
                                "type": "STRING"
                              },
                              {
                                "mode": "NULLABLE",
                                "name": "headerValue",
                                "type": "STRING"
                              },
                              {
                                "mode": "NULLABLE",
                                "name": "replace",
                                "type": "BOOLEAN"
                              }
                            ],
                            "mode": "REPEATED",
                            "name": "requestHeadersToAdd",
                            "type": "RECORD"
                          },
                          {
                            "mode": "REPEATED",
                            "name": "responseHeadersToRemove",
                            "type": "STRING"
                          },
                          {
                            "fields": [
                              {
                                "mode": "NULLABLE",
                                "name": "headerName",
                                "type": "STRING"
                              },
                              {
                                "mode": "NULLABLE",
                                "name": "headerValue",
                                "type": "STRING"
                              },
                              {
                                "mode": "NULLABLE",
                                "name": "replace",
                                "type": "BOOLEAN"
                              }
                            ],
                            "mode": "REPEATED",
                            "name": "responseHeadersToAdd",
                            "type": "RECORD"
                          }
                        ],
                        "mode": "NULLABLE",
                        "name": "headerAction",
                        "type": "RECORD"
                      }
                    ],
                    "mode": "REPEATED",
                    "name": "weightedBackendServices",
                    "type": "RECORD"
                  },
                  {
                    "fields": [
                      {
                        "mode": "NULLABLE",
                        "name": "backendService",
                        "type": "STRING"
                      },
                      {
                        "mode": "NULLABLE",
                        "name": "weight",
                        "type": "INTEGER"
                      },
                      {
                        "fields": [
                          {
                            "mode": "REPEATED",
                            "name": "requestHeadersToRemove",
                            "type": "STRING"
                          },
                          {
                            "fields": [
                              {
                                "mode": "NULLABLE",
                                "name": "headerName",
                                "type": "STRING"
                              },
                              {
                                "mode": "NULLABLE",
                                "name": "headerValue",
                                "type": "STRING"
                              },
                              {
                                "mode": "NULLABLE",
                                "name": "replace",
                                "type": "BOOLEAN"
                              }
                            ],
                            "mode": "REPEATED",
                            "name": "requestHeadersToAdd",
                            "type": "RECORD"
                          },
                          {
                            "mode": "REPEATED",
                            "name": "responseHeadersToRemove",
                            "type": "STRING"
                          },
                          {
                            "fields": [
                              {
                                "mode": "NULLABLE",
                                "name": "headerName",
                                "type": "STRING"
                              },
                              {
                                "mode": "NULLABLE",
                                "name": "headerValue",
                                "type": "STRING"
                              },
                              {
                                "mode": "NULLABLE",
                                "name": "replace",
                                "type": "BOOLEAN"
                              }
                            ],
                            "mode": "REPEATED",
                            "name": "responseHeadersToAdd",
                            "type": "RECORD"
                          }
                        ],
                        "mode": "NULLABLE",
                        "name": "headerAction",
                        "type": "RECORD"
                      }
                    ],
                    "mode": "REPEATED",
                    "name": "weightedBackendService",
                    "type": "RECORD"
                  },
                  {
                    "fields": [
                      {
                        "mode": "NULLABLE",
                        "name": "pathPrefixRewrite",
                        "type": "STRING"
                      },
                      {
                        "mode": "NULLABLE",
                        "name": "hostRewrite",
                        "type": "STRING"
                      },
                      {
                        "mode": "NULLABLE",
                        "name": "pathTemplateRewrite",
                        "type": "STRING"
                      }
                    ],
                    "mode": "NULLABLE",
                    "name": "urlRewrite",
                    "type": "RECORD"
                  },
                  {
                    "fields": [
                      {
                        "mode": "NULLABLE",
                        "name": "seconds",
                        "type": "STRING"
                      },
                      {
                        "mode": "NULLABLE",
                        "name": "nanos",
                        "type": "INTEGER"
                      }
                    ],
                    "mode": "NULLABLE",
                    "name": "timeout",
                    "type": "RECORD"
                  },
                  {
                    "fields": [
                      {
                        "mode": "REPEATED",
                        "name": "retryConditions",
                        "type": "STRING"
                      },
                      {
                        "mode": "REPEATED",
                        "name": "retryCondition",
                        "type": "STRING"
                      },
                      {
                        "mode": "NULLABLE",
                        "name": "numRetries",
                        "type": "INTEGER"
                      },
                      {
                        "fields": [
                          {
                            "mode": "NULLABLE",
                            "name": "seconds",
                            "type": "STRING"
                          },
                          {
                            "mode": "NULLABLE",
                            "name": "nanos",
                            "type": "INTEGER"
                          }
                        ],
                        "mode": "NULLABLE",
                        "name": "perTryTimeout",
                        "type": "RECORD"
                      }
                    ],
                    "mode": "NULLABLE",
                    "name": "retryPolicy",
                    "type": "RECORD"
                  },
                  {
                    "fields": [
                      {
                        "mode": "NULLABLE",
                        "name": "backendService",
                        "type": "STRING"
                      }
                    ],
                    "mode": "NULLABLE",
                    "name": "requestMirrorPolicy",
                    "type": "RECORD"
                  },
                  {
                    "fields": [
                      {
                        "mode": "REPEATED",
                        "name": "allowOrigins",
                        "type": "STRING"
                      },
                      {
                        "mode": "REPEATED",
                        "name": "allowOrigin",
                        "type": "STRING"
                      },
                      {
                        "mode": "REPEATED",
                        "name": "allowOriginRegexes",
                        "type": "STRING"
                      },
                      {
                        "mode": "REPEATED",
                        "name": "allowOriginRegex",
                        "type": "STRING"
                      },
                      {
                        "mode": "REPEATED",
                        "name": "allowMethods",
                        "type": "STRING"
                      },
                      {
                        "mode": "REPEATED",
                        "name": "allowMethod",
                        "type": "STRING"
                      },
                      {
                        "mode": "REPEATED",
                        "name": "allowHeaders",
                        "type": "STRING"
                      },
                      {
                        "mode": "REPEATED",
                        "name": "allowHeader",
                        "type": "STRING"
                      },
                      {
                        "mode": "REPEATED",
                        "name": "exposeHeaders",
                        "type": "STRING"
                      },
                      {
                        "mode": "REPEATED",
                        "name": "exposeHeader",
                        "type": "STRING"
                      },
                      {
                        "mode": "NULLABLE",
                        "name": "maxAge",
                        "type": "INTEGER"
                      },
                      {
                        "mode": "NULLABLE",
                        "name": "allowCredentials",
                        "type": "BOOLEAN"
                      },
                      {
                        "mode": "NULLABLE",
                        "name": "disabled",
                        "type": "BOOLEAN"
                      }
                    ],
                    "mode": "NULLABLE",
                    "name": "corsPolicy",
                    "type": "RECORD"
                  },
                  {
                    "fields": [
                      {
                        "fields": [
                          {
                            "fields": [
                              {
                                "mode": "NULLABLE",
                                "name": "seconds",
                                "type": "STRING"
                              },
                              {
                                "mode": "NULLABLE",
                                "name": "nanos",
                                "type": "INTEGER"
                              }
                            ],
                            "mode": "NULLABLE",
                            "name": "fixedDelay",
                            "type": "RECORD"
                          },
                          {
                            "mode": "NULLABLE",
                            "name": "percentage",
                            "type": "FLOAT"
                          }
                        ],
                        "mode": "NULLABLE",
                        "name": "delay",
                        "type": "RECORD"
                      },
                      {
                        "fields": [
                          {
                            "mode": "NULLABLE",
                            "name": "httpStatus",
                            "type": "INTEGER"
                          },
                          {
                            "mode": "NULLABLE",
                            "name": "percentage",
                            "type": "FLOAT"
                          }
                        ],
                        "mode": "NULLABLE",
                        "name": "abort",
                        "type": "RECORD"
                      }
                    ],
                    "mode": "NULLABLE",
                    "name": "faultInjectionPolicy",
                    "type": "RECORD"
                  },
                  {
                    "fields": [
                      {
                        "mode": "NULLABLE",
                        "name": "seconds",
                        "type": "STRING"
                      },
                      {
                        "mode": "NULLABLE",
                        "name": "nanos",
                        "type": "INTEGER"
                      }
                    ],
                    "mode": "NULLABLE",
                    "name": "maxStreamDuration",
                    "type": "RECORD"
                  }
                ],
                "mode": "NULLABLE",
                "name": "defaultRouteAction",
                "type": "RECORD"
              },
              {
                "fields": [
                  {
                    "mode": "NULLABLE",
                    "name": "hostRedirect",
                    "type": "STRING"
                  },
                  {
                    "mode": "NULLABLE",
                    "name": "pathRedirect",
                    "type": "STRING"
                  },
                  {
                    "mode": "NULLABLE",
                    "name": "prefixRedirect",
                    "type": "STRING"
                  },
                  {
                    "mode": "NULLABLE",
                    "name": "redirectResponseCode",
                    "type": "STRING"
                  },
                  {
                    "mode": "NULLABLE",
                    "name": "httpsRedirect",
                    "type": "BOOLEAN"
                  },
                  {
                    "mode": "NULLABLE",
                    "name": "stripQuery",
                    "type": "BOOLEAN"
                  }
                ],
                "mode": "NULLABLE",
                "name": "defaultUrlRedirect",
                "type": "RECORD"
              },
              {
                "fields": [
                  {
                    "mode": "NULLABLE",
                    "name": "service",
                    "type": "STRING"
                  },
                  {
                    "fields": [
                      {
                        "fields": [
                          {
                            "mode": "NULLABLE",
                            "name": "backendService",
                            "type": "STRING"
                          },
                          {
                            "mode": "NULLABLE",
                            "name": "weight",
                            "type": "INTEGER"
                          },
                          {
                            "fields": [
                              {
                                "mode": "REPEATED",
                                "name": "requestHeadersToRemove",
                                "type": "STRING"
                              },
                              {
                                "fields": [
                                  {
                                    "mode": "NULLABLE",
                                    "name": "headerName",
                                    "type": "STRING"
                                  },
                                  {
                                    "mode": "NULLABLE",
                                    "name": "headerValue",
                                    "type": "STRING"
                                  },
                                  {
                                    "mode": "NULLABLE",
                                    "name": "replace",
                                    "type": "BOOLEAN"
                                  }
                                ],
                                "mode": "REPEATED",
                                "name": "requestHeadersToAdd",
                                "type": "RECORD"
                              },
                              {
                                "mode": "REPEATED",
                                "name": "responseHeadersToRemove",
                                "type": "STRING"
                              },
                              {
                                "fields": [
                                  {
                                    "mode": "NULLABLE",
                                    "name": "headerName",
                                    "type": "STRING"
                                  },
                                  {
                                    "mode": "NULLABLE",
                                    "name": "headerValue",
                                    "type": "STRING"
                                  },
                                  {
                                    "mode": "NULLABLE",
                                    "name": "replace",
                                    "type": "BOOLEAN"
                                  }
                                ],
                                "mode": "REPEATED",
                                "name": "responseHeadersToAdd",
                                "type": "RECORD"
                              }
                            ],
                            "mode": "NULLABLE",
                            "name": "headerAction",
                            "type": "RECORD"
                          }
                        ],
                        "mode": "REPEATED",
                        "name": "weightedBackendServices",
                        "type": "RECORD"
                      },
                      {
                        "fields": [
                          {
                            "mode": "NULLABLE",
                            "name": "backendService",
                            "type": "STRING"
                          },
                          {
                            "mode": "NULLABLE",
                            "name": "weight",
                            "type": "INTEGER"
                          },
                          {
                            "fields": [
                              {
                                "mode": "REPEATED",
                                "name": "requestHeadersToRemove",
                                "type": "STRING"
                              },
                              {
                                "fields": [
                                  {
                                    "mode": "NULLABLE",
                                    "name": "headerName",
                                    "type": "STRING"
                                  },
                                  {
                                    "mode": "NULLABLE",
                                    "name": "headerValue",
                                    "type": "STRING"
                                  },
                                  {
                                    "mode": "NULLABLE",
                                    "name": "replace",
                                    "type": "BOOLEAN"
                                  }
                                ],
                                "mode": "REPEATED",
                                "name": "requestHeadersToAdd",
                                "type": "RECORD"
                              },
                              {
                                "mode": "REPEATED",
                                "name": "responseHeadersToRemove",
                                "type": "STRING"
                              },
                              {
                                "fields": [
                                  {
                                    "mode": "NULLABLE",
                                    "name": "headerName",
                                    "type": "STRING"
                                  },
                                  {
                                    "mode": "NULLABLE",
                                    "name": "headerValue",
                                    "type": "STRING"
                                  },
                                  {
                                    "mode": "NULLABLE",
                                    "name": "replace",
                                    "type": "BOOLEAN"
                                  }
                                ],
                                "mode": "REPEATED",
                                "name": "responseHeadersToAdd",
                                "type": "RECORD"
                              }
                            ],
                            "mode": "NULLABLE",
                            "name": "headerAction",
                            "type": "RECORD"
                          }
                        ],
                        "mode": "REPEATED",
                        "name": "weightedBackendService",
                        "type": "RECORD"
                      },
                      {
                        "fields": [
                          {
                            "mode": "NULLABLE",
                            "name": "pathPrefixRewrite",
                            "type": "STRING"
                          },
                          {
                            "mode": "NULLABLE",
                            "name": "hostRewrite",
                            "type": "STRING"
                          },
                          {
                            "mode": "NULLABLE",
                            "name": "pathTemplateRewrite",
                            "type": "STRING"
                          }
                        ],
                        "mode": "NULLABLE",
                        "name": "urlRewrite",
                        "type": "RECORD"
                      },
                      {
                        "fields": [
                          {
                            "mode": "NULLABLE",
                            "name": "seconds",
                            "type": "STRING"
                          },
                          {
                            "mode": "NULLABLE",
                            "name": "nanos",
                            "type": "INTEGER"
                          }
                        ],
                        "mode": "NULLABLE",
                        "name": "timeout",
                        "type": "RECORD"
                      },
                      {
                        "fields": [
                          {
                            "mode": "REPEATED",
                            "name": "retryConditions",
                            "type": "STRING"
                          },
                          {
                            "mode": "REPEATED",
                            "name": "retryCondition",
                            "type": "STRING"
                          },
                          {
                            "mode": "NULLABLE",
                            "name": "numRetries",
                            "type": "INTEGER"
                          },
                          {
                            "fields": [
                              {
                                "mode": "NULLABLE",
                                "name": "seconds",
                                "type": "STRING"
                              },
                              {
                                "mode": "NULLABLE",
                                "name": "nanos",
                                "type": "INTEGER"
                              }
                            ],
                            "mode": "NULLABLE",
                            "name": "perTryTimeout",
                            "type": "RECORD"
                          }
                        ],
                        "mode": "NULLABLE",
                        "name": "retryPolicy",
                        "type": "RECORD"
                      },
                      {
                        "fields": [
                          {
                            "mode": "NULLABLE",
                            "name": "backendService",
                            "type": "STRING"
                          }
                        ],
                        "mode": "NULLABLE",
                        "name": "requestMirrorPolicy",
                        "type": "RECORD"
                      },
                      {
                        "fields": [
                          {
                            "mode": "REPEATED",
                            "name": "allowOrigins",
                            "type": "STRING"
                          },
                          {
                            "mode": "REPEATED",
                            "name": "allowOrigin",
                            "type": "STRING"
                          },
                          {
                            "mode": "REPEATED",
                            "name": "allowOriginRegexes",
                            "type": "STRING"
                          },
                          {
                            "mode": "REPEATED",
                            "name": "allowOriginRegex",
                            "type": "STRING"
                          },
                          {
                            "mode": "REPEATED",
                            "name": "allowMethods",
                            "type": "STRING"
                          },
                          {
                            "mode": "REPEATED",
                            "name": "allowMethod",
                            "type": "STRING"
                          },
                          {
                            "mode": "REPEATED",
                            "name": "allowHeaders",
                            "type": "STRING"
                          },
                          {
                            "mode": "REPEATED",
                            "name": "allowHeader",
                            "type": "STRING"
                          },
                          {
                            "mode": "REPEATED",
                            "name": "exposeHeaders",
                            "type": "STRING"
                          },
                          {
                            "mode": "REPEATED",
                            "name": "exposeHeader",
                            "type": "STRING"
                          },
                          {
                            "mode": "NULLABLE",
                            "name": "maxAge",
                            "type": "INTEGER"
                          },
                          {
                            "mode": "NULLABLE",
                            "name": "allowCredentials",
                            "type": "BOOLEAN"
                          },
                          {
                            "mode": "NULLABLE",
                            "name": "disabled",
                            "type": "BOOLEAN"
                          }
                        ],
                        "mode": "NULLABLE",
                        "name": "corsPolicy",
                        "type": "RECORD"
                      },
                      {
                        "fields": [
                          {
                            "fields": [
                              {
                                "fields": [
                                  {
                                    "mode": "NULLABLE",
                                    "name": "seconds",
                                    "type": "STRING"
                                  },
                                  {
                                    "mode": "NULLABLE",
                                    "name": "nanos",
                                    "type": "INTEGER"
                                  }
                                ],
                                "mode": "NULLABLE",
                                "name": "fixedDelay",
                                "type": "RECORD"
                              },
                              {
                                "mode": "NULLABLE",
                                "name": "percentage",
                                "type": "FLOAT"
                              }
                            ],
                            "mode": "NULLABLE",
                            "name": "delay",
                            "type": "RECORD"
                          },
                          {
                            "fields": [
                              {
                                "mode": "NULLABLE",
                                "name": "httpStatus",
                                "type": "INTEGER"
                              },
                              {
                                "mode": "NULLABLE",
                                "name": "percentage",
                                "type": "FLOAT"
                              }
                            ],
                            "mode": "NULLABLE",
                            "name": "abort",
                            "type": "RECORD"
                          }
                        ],
                        "mode": "NULLABLE",
                        "name": "faultInjectionPolicy",
                        "type": "RECORD"
                      },
                      {
                        "fields": [
                          {
                            "mode": "NULLABLE",
                            "name": "seconds",
                            "type": "STRING"
                          },
                          {
                            "mode": "NULLABLE",
                            "name": "nanos",
                            "type": "INTEGER"
                          }
                        ],
                        "mode": "NULLABLE",
                        "name": "maxStreamDuration",
                        "type": "RECORD"
                      }
                    ],
                    "mode": "NULLABLE",
                    "name": "routeAction",
                    "type": "RECORD"
                  },
                  {
                    "fields": [
                      {
                        "mode": "NULLABLE",
                        "name": "hostRedirect",
                        "type": "STRING"
                      },
                      {
                        "mode": "NULLABLE",
                        "name": "pathRedirect",
                        "type": "STRING"
                      },
                      {
                        "mode": "NULLABLE",
                        "name": "prefixRedirect",
                        "type": "STRING"
                      },
                      {
                        "mode": "NULLABLE",
                        "name": "redirectResponseCode",
                        "type": "STRING"
                      },
                      {
                        "mode": "NULLABLE",
                        "name": "httpsRedirect",
                        "type": "BOOLEAN"
                      },
                      {
                        "mode": "NULLABLE",
                        "name": "stripQuery",
                        "type": "BOOLEAN"
                      }
                    ],
                    "mode": "NULLABLE",
                    "name": "urlRedirect",
                    "type": "RECORD"
                  },
                  {
                    "mode": "REPEATED",
                    "name": "paths",
                    "type": "STRING"
                  },
                  {
                    "fields": [
                      {
                        "mode": "NULLABLE",
                        "name": "errorService",
                        "type": "STRING"
                      }
                    ],
                    "mode": "NULLABLE",
                    "name": "customErrorResponsePolicy",
                    "type": "RECORD"
                  }
                ],
                "mode": "REPEATED",
                "name": "pathRules",
                "type": "RECORD"
              },
              {
                "fields": [
                  {
                    "mode": "NULLABLE",
                    "name": "priority",
                    "type": "INTEGER"
                  },
                  {
                    "mode": "NULLABLE",
                    "name": "description",
                    "type": "STRING"
                  },
                  {
                    "fields": [
                      {
                        "mode": "NULLABLE",
                        "name": "prefixMatch",
                        "type": "STRING"
                      },
                      {
                        "mode": "NULLABLE",
                        "name": "fullPathMatch",
                        "type": "STRING"
                      },
                      {
                        "mode": "NULLABLE",
                        "name": "regexMatch",
                        "type": "STRING"
                      },
                      {
                        "mode": "NULLABLE",
                        "name": "ignoreCase",
                        "type": "BOOLEAN"
                      },
                      {
                        "fields": [
                          {
                            "mode": "NULLABLE",
                            "name": "headerName",
                            "type": "STRING"
                          },
                          {
                            "mode": "NULLABLE",
                            "name": "exactMatch",
                            "type": "STRING"
                          },
                          {
                            "mode": "NULLABLE",
                            "name": "regexMatch",
                            "type": "STRING"
                          },
                          {
                            "fields": [
                              {
                                "mode": "NULLABLE",
                                "name": "rangeStart",
                                "type": "STRING"
                              },
                              {
                                "mode": "NULLABLE",
                                "name": "rangeEnd",
                                "type": "STRING"
                              }
                            ],
                            "mode": "NULLABLE",
                            "name": "rangeMatch",
                            "type": "RECORD"
                          },
                          {
                            "mode": "NULLABLE",
                            "name": "presentMatch",
                            "type": "BOOLEAN"
                          },
                          {
                            "mode": "NULLABLE",
                            "name": "prefixMatch",
                            "type": "STRING"
                          },
                          {
                            "mode": "NULLABLE",
                            "name": "suffixMatch",
                            "type": "STRING"
                          },
                          {
                            "mode": "NULLABLE",
                            "name": "invertMatch",
                            "type": "BOOLEAN"
                          }
                        ],
                        "mode": "REPEATED",
                        "name": "headerMatches",
                        "type": "RECORD"
                      },
                      {
                        "fields": [
                          {
                            "mode": "NULLABLE",
                            "name": "name",
                            "type": "STRING"
                          },
                          {
                            "mode": "NULLABLE",
                            "name": "presentMatch",
                            "type": "BOOLEAN"
                          },
                          {
                            "mode": "NULLABLE",
                            "name": "exactMatch",
                            "type": "STRING"
                          },
                          {
                            "mode": "NULLABLE",
                            "name": "regexMatch",
                            "type": "STRING"
                          }
                        ],
                        "mode": "REPEATED",
                        "name": "queryParameterMatches",
                        "type": "RECORD"
                      },
                      {
                        "fields": [
                          {
                            "mode": "NULLABLE",
                            "name": "filterMatchCriteria",
                            "type": "STRING"
                          },
                          {
                            "fields": [
                              {
                                "mode": "NULLABLE",
                                "name": "name",
                                "type": "STRING"
                              },
                              {
                                "mode": "NULLABLE",
                                "name": "value",
                                "type": "STRING"
                              }
                            ],
                            "mode": "REPEATED",
                            "name": "filterLabels",
                            "type": "RECORD"
                          }
                        ],
                        "mode": "REPEATED",
                        "name": "metadataFilters",
                        "type": "RECORD"
                      },
                      {
                        "mode": "NULLABLE",
                        "name": "pathTemplateMatch",
                        "type": "STRING"
                      }
                    ],
                    "mode": "REPEATED",
                    "name": "matchRules",
                    "type": "RECORD"
                  },
                  {
                    "mode": "NULLABLE",
                    "name": "service",
                    "type": "STRING"
                  },
                  {
                    "mode": "NULLABLE",
                    "name": "backendService",
                    "type": "STRING"
                  },
                  {
                    "fields": [
                      {
                        "fields": [
                          {
                            "mode": "NULLABLE",
                            "name": "backendService",
                            "type": "STRING"
                          },
                          {
                            "mode": "NULLABLE",
                            "name": "weight",
                            "type": "INTEGER"
                          },
                          {
                            "fields": [
                              {
                                "mode": "REPEATED",
                                "name": "requestHeadersToRemove",
                                "type": "STRING"
                              },
                              {
                                "fields": [
                                  {
                                    "mode": "NULLABLE",
                                    "name": "headerName",
                                    "type": "STRING"
                                  },
                                  {
                                    "mode": "NULLABLE",
                                    "name": "headerValue",
                                    "type": "STRING"
                                  },
                                  {
                                    "mode": "NULLABLE",
                                    "name": "replace",
                                    "type": "BOOLEAN"
                                  }
                                ],
                                "mode": "REPEATED",
                                "name": "requestHeadersToAdd",
                                "type": "RECORD"
                              },
                              {
                                "mode": "REPEATED",
                                "name": "responseHeadersToRemove",
                                "type": "STRING"
                              },
                              {
                                "fields": [
                                  {
                                    "mode": "NULLABLE",
                                    "name": "headerName",
                                    "type": "STRING"
                                  },
                                  {
                                    "mode": "NULLABLE",
                                    "name": "headerValue",
                                    "type": "STRING"
                                  },
                                  {
                                    "mode": "NULLABLE",
                                    "name": "replace",
                                    "type": "BOOLEAN"
                                  }
                                ],
                                "mode": "REPEATED",
                                "name": "responseHeadersToAdd",
                                "type": "RECORD"
                              }
                            ],
                            "mode": "NULLABLE",
                            "name": "headerAction",
                            "type": "RECORD"
                          }
                        ],
                        "mode": "REPEATED",
                        "name": "weightedBackendServices",
                        "type": "RECORD"
                      },
                      {
                        "fields": [
                          {
                            "mode": "NULLABLE",
                            "name": "backendService",
                            "type": "STRING"
                          },
                          {
                            "mode": "NULLABLE",
                            "name": "weight",
                            "type": "INTEGER"
                          },
                          {
                            "fields": [
                              {
                                "mode": "REPEATED",
                                "name": "requestHeadersToRemove",
                                "type": "STRING"
                              },
                              {
                                "fields": [
                                  {
                                    "mode": "NULLABLE",
                                    "name": "headerName",
                                    "type": "STRING"
                                  },
                                  {
                                    "mode": "NULLABLE",
                                    "name": "headerValue",
                                    "type": "STRING"
                                  },
                                  {
                                    "mode": "NULLABLE",
                                    "name": "replace",
                                    "type": "BOOLEAN"
                                  }
                                ],
                                "mode": "REPEATED",
                                "name": "requestHeadersToAdd",
                                "type": "RECORD"
                              },
                              {
                                "mode": "REPEATED",
                                "name": "responseHeadersToRemove",
                                "type": "STRING"
                              },
                              {
                                "fields": [
                                  {
                                    "mode": "NULLABLE",
                                    "name": "headerName",
                                    "type": "STRING"
                                  },
                                  {
                                    "mode": "NULLABLE",
                                    "name": "headerValue",
                                    "type": "STRING"
                                  },
                                  {
                                    "mode": "NULLABLE",
                                    "name": "replace",
                                    "type": "BOOLEAN"
                                  }
                                ],
                                "mode": "REPEATED",
                                "name": "responseHeadersToAdd",
                                "type": "RECORD"
                              }
                            ],
                            "mode": "NULLABLE",
                            "name": "headerAction",
                            "type": "RECORD"
                          }
                        ],
                        "mode": "REPEATED",
                        "name": "weightedBackendService",
                        "type": "RECORD"
                      },
                      {
                        "fields": [
                          {
                            "mode": "NULLABLE",
                            "name": "pathPrefixRewrite",
                            "type": "STRING"
                          },
                          {
                            "mode": "NULLABLE",
                            "name": "hostRewrite",
                            "type": "STRING"
                          },
                          {
                            "mode": "NULLABLE",
                            "name": "pathTemplateRewrite",
                            "type": "STRING"
                          }
                        ],
                        "mode": "NULLABLE",
                        "name": "urlRewrite",
                        "type": "RECORD"
                      },
                      {
                        "fields": [
                          {
                            "mode": "NULLABLE",
                            "name": "seconds",
                            "type": "STRING"
                          },
                          {
                            "mode": "NULLABLE",
                            "name": "nanos",
                            "type": "INTEGER"
                          }
                        ],
                        "mode": "NULLABLE",
                        "name": "timeout",
                        "type": "RECORD"
                      },
                      {
                        "fields": [
                          {
                            "mode": "REPEATED",
                            "name": "retryConditions",
                            "type": "STRING"
                          },
                          {
                            "mode": "REPEATED",
                            "name": "retryCondition",
                            "type": "STRING"
                          },
                          {
                            "mode": "NULLABLE",
                            "name": "numRetries",
                            "type": "INTEGER"
                          },
                          {
                            "fields": [
                              {
                                "mode": "NULLABLE",
                                "name": "seconds",
                                "type": "STRING"
                              },
                              {
                                "mode": "NULLABLE",
                                "name": "nanos",
                                "type": "INTEGER"
                              }
                            ],
                            "mode": "NULLABLE",
                            "name": "perTryTimeout",
                            "type": "RECORD"
                          }
                        ],
                        "mode": "NULLABLE",
                        "name": "retryPolicy",
                        "type": "RECORD"
                      },
                      {
                        "fields": [
                          {
                            "mode": "NULLABLE",
                            "name": "backendService",
                            "type": "STRING"
                          }
                        ],
                        "mode": "NULLABLE",
                        "name": "requestMirrorPolicy",
                        "type": "RECORD"
                      },
                      {
                        "fields": [
                          {
                            "mode": "REPEATED",
                            "name": "allowOrigins",
                            "type": "STRING"
                          },
                          {
                            "mode": "REPEATED",
                            "name": "allowOrigin",
                            "type": "STRING"
                          },
                          {
                            "mode": "REPEATED",
                            "name": "allowOriginRegexes",
                            "type": "STRING"
                          },
                          {
                            "mode": "REPEATED",
                            "name": "allowOriginRegex",
                            "type": "STRING"
                          },
                          {
                            "mode": "REPEATED",
                            "name": "allowMethods",
                            "type": "STRING"
                          },
                          {
                            "mode": "REPEATED",
                            "name": "allowMethod",
                            "type": "STRING"
                          },
                          {
                            "mode": "REPEATED",
                            "name": "allowHeaders",
                            "type": "STRING"
                          },
                          {
                            "mode": "REPEATED",
                            "name": "allowHeader",
                            "type": "STRING"
                          },
                          {
                            "mode": "REPEATED",
                            "name": "exposeHeaders",
                            "type": "STRING"
                          },
                          {
                            "mode": "REPEATED",
                            "name": "exposeHeader",
                            "type": "STRING"
                          },
                          {
                            "mode": "NULLABLE",
                            "name": "maxAge",
                            "type": "INTEGER"
                          },
                          {
                            "mode": "NULLABLE",
                            "name": "allowCredentials",
                            "type": "BOOLEAN"
                          },
                          {
                            "mode": "NULLABLE",
                            "name": "disabled",
                            "type": "BOOLEAN"
                          }
                        ],
                        "mode": "NULLABLE",
                        "name": "corsPolicy",
                        "type": "RECORD"
                      },
                      {
                        "fields": [
                          {
                            "fields": [
                              {
                                "fields": [
                                  {
                                    "mode": "NULLABLE",
                                    "name": "seconds",
                                    "type": "STRING"
                                  },
                                  {
                                    "mode": "NULLABLE",
                                    "name": "nanos",
                                    "type": "INTEGER"
                                  }
                                ],
                                "mode": "NULLABLE",
                                "name": "fixedDelay",
                                "type": "RECORD"
                              },
                              {
                                "mode": "NULLABLE",
                                "name": "percentage",
                                "type": "FLOAT"
                              }
                            ],
                            "mode": "NULLABLE",
                            "name": "delay",
                            "type": "RECORD"
                          },
                          {
                            "fields": [
                              {
                                "mode": "NULLABLE",
                                "name": "httpStatus",
                                "type": "INTEGER"
                              },
                              {
                                "mode": "NULLABLE",
                                "name": "percentage",
                                "type": "FLOAT"
                              }
                            ],
                            "mode": "NULLABLE",
                            "name": "abort",
                            "type": "RECORD"
                          }
                        ],
                        "mode": "NULLABLE",
                        "name": "faultInjectionPolicy",
                        "type": "RECORD"
                      },
                      {
                        "fields": [
                          {
                            "mode": "NULLABLE",
                            "name": "seconds",
                            "type": "STRING"
                          },
                          {
                            "mode": "NULLABLE",
                            "name": "nanos",
                            "type": "INTEGER"
                          }
                        ],
                        "mode": "NULLABLE",
                        "name": "maxStreamDuration",
                        "type": "RECORD"
                      }
                    ],
                    "mode": "NULLABLE",
                    "name": "routeAction",
                    "type": "RECORD"
                  },
                  {
                    "fields": [
                      {
                        "mode": "NULLABLE",
                        "name": "hostRedirect",
                        "type": "STRING"
                      },
                      {
                        "mode": "NULLABLE",
                        "name": "pathRedirect",
                        "type": "STRING"
                      },
                      {
                        "mode": "NULLABLE",
                        "name": "prefixRedirect",
                        "type": "STRING"
                      },
                      {
                        "mode": "NULLABLE",
                        "name": "redirectResponseCode",
                        "type": "STRING"
                      },
                      {
                        "mode": "NULLABLE",
                        "name": "httpsRedirect",
                        "type": "BOOLEAN"
                      },
                      {
                        "mode": "NULLABLE",
                        "name": "stripQuery",
                        "type": "BOOLEAN"
                      }
                    ],
                    "mode": "NULLABLE",
                    "name": "urlRedirect",
                    "type": "RECORD"
                  },
                  {
                    "fields": [
                      {
                        "mode": "REPEATED",
                        "name": "requestHeadersToRemove",
                        "type": "STRING"
                      },
                      {
                        "fields": [
                          {
                            "mode": "NULLABLE",
                            "name": "headerName",
                            "type": "STRING"
                          },
                          {
                            "mode": "NULLABLE",
                            "name": "headerValue",
                            "type": "STRING"
                          },
                          {
                            "mode": "NULLABLE",
                            "name": "replace",
                            "type": "BOOLEAN"
                          }
                        ],
                        "mode": "REPEATED",
                        "name": "requestHeadersToAdd",
                        "type": "RECORD"
                      },
                      {
                        "mode": "REPEATED",
                        "name": "responseHeadersToRemove",
                        "type": "STRING"
                      },
                      {
                        "fields": [
                          {
                            "mode": "NULLABLE",
                            "name": "headerName",
                            "type": "STRING"
                          },
                          {
                            "mode": "NULLABLE",
                            "name": "headerValue",
                            "type": "STRING"
                          },
                          {
                            "mode": "NULLABLE",
                            "name": "replace",
                            "type": "BOOLEAN"
                          }
                        ],
                        "mode": "REPEATED",
                        "name": "responseHeadersToAdd",
                        "type": "RECORD"
                      }
                    ],
                    "mode": "NULLABLE",
                    "name": "headerAction",
                    "type": "RECORD"
                  },
                  {
                    "fields": [
                      {
                        "mode": "NULLABLE",
                        "name": "errorService",
                        "type": "STRING"
                      }
                    ],
                    "mode": "NULLABLE",
                    "name": "customErrorResponsePolicy",
                    "type": "RECORD"
                  }
                ],
                "mode": "REPEATED",
                "name": "routeRules",
                "type": "RECORD"
              },
              {
                "fields": [
                  {
                    "mode": "REPEATED",
                    "name": "requestHeadersToRemove",
                    "type": "STRING"
                  },
                  {
                    "fields": [
                      {
                        "mode": "NULLABLE",
                        "name": "headerName",
                        "type": "STRING"
                      },
                      {
                        "mode": "NULLABLE",
                        "name": "headerValue",
                        "type": "STRING"
                      },
                      {
                        "mode": "NULLABLE",
                        "name": "replace",
                        "type": "BOOLEAN"
                      }
                    ],
                    "mode": "REPEATED",
                    "name": "requestHeadersToAdd",
                    "type": "RECORD"
                  },
                  {
                    "mode": "REPEATED",
                    "name": "responseHeadersToRemove",
                    "type": "STRING"
                  },
                  {
                    "fields": [
                      {
                        "mode": "NULLABLE",
                        "name": "headerName",
                        "type": "STRING"
                      },
                      {
                        "mode": "NULLABLE",
                        "name": "headerValue",
                        "type": "STRING"
                      },
                      {
                        "mode": "NULLABLE",
                        "name": "replace",
                        "type": "BOOLEAN"
                      }
                    ],
                    "mode": "REPEATED",
                    "name": "responseHeadersToAdd",
                    "type": "RECORD"
                  }
                ],
                "mode": "NULLABLE",
                "name": "headerAction",
                "type": "RECORD"
              },
              {
                "fields": [
                  {
                    "mode": "NULLABLE",
                    "name": "errorService",
                    "type": "STRING"
                  }
                ],
                "mode": "NULLABLE",
                "name": "defaultCustomErrorResponsePolicy",
                "type": "RECORD"
              }
            ],
            "mode": "REPEATED",
            "name": "pathMatchers",
            "type": "RECORD"
          },
          {
            "fields": [
              {
                "mode": "NULLABLE",
                "name": "description",
                "type": "STRING"
              },
              {
                "mode": "NULLABLE",
                "name": "host",
                "type": "STRING"
              },
              {
                "mode": "NULLABLE",
                "name": "path",
                "type": "STRING"
              },
              {
                "fields": [
                  {
                    "mode": "NULLABLE",
                    "name": "name",
                    "type": "STRING"
                  },
                  {
                    "mode": "NULLABLE",
                    "name": "value",
                    "type": "STRING"
                  }
                ],
                "mode": "REPEATED",
                "name": "headers",
                "type": "RECORD"
              },
              {
                "mode": "NULLABLE",
                "name": "service",
                "type": "STRING"
              },
              {
                "mode": "NULLABLE",
                "name": "expectedOutputUrl",
                "type": "STRING"
              },
              {
                "mode": "NULLABLE",
                "name": "expectedRedirectResponseCode",
                "type": "INTEGER"
              }
            ],
            "mode": "REPEATED",
            "name": "tests",
            "type": "RECORD"
          },
          {
            "mode": "NULLABLE",
            "name": "defaultService",
            "type": "STRING"
          },
          {
            "fields": [
              {
                "fields": [
                  {
                    "mode": "NULLABLE",
                    "name": "backendService",
                    "type": "STRING"
                  },
                  {
                    "mode": "NULLABLE",
                    "name": "weight",
                    "type": "INTEGER"
                  },
                  {
                    "fields": [
                      {
                        "mode": "REPEATED",
                        "name": "requestHeadersToRemove",
                        "type": "STRING"
                      },
                      {
                        "fields": [
                          {
                            "mode": "NULLABLE",
                            "name": "headerName",
                            "type": "STRING"
                          },
                          {
                            "mode": "NULLABLE",
                            "name": "headerValue",
                            "type": "STRING"
                          },
                          {
                            "mode": "NULLABLE",
                            "name": "replace",
                            "type": "BOOLEAN"
                          }
                        ],
                        "mode": "REPEATED",
                        "name": "requestHeadersToAdd",
                        "type": "RECORD"
                      },
                      {
                        "mode": "REPEATED",
                        "name": "responseHeadersToRemove",
                        "type": "STRING"
                      },
                      {
                        "fields": [
                          {
                            "mode": "NULLABLE",
                            "name": "headerName",
                            "type": "STRING"
                          },
                          {
                            "mode": "NULLABLE",
                            "name": "headerValue",
                            "type": "STRING"
                          },
                          {
                            "mode": "NULLABLE",
                            "name": "replace",
                            "type": "BOOLEAN"
                          }
                        ],
                        "mode": "REPEATED",
                        "name": "responseHeadersToAdd",
                        "type": "RECORD"
                      }
                    ],
                    "mode": "NULLABLE",
                    "name": "headerAction",
                    "type": "RECORD"
                  }
                ],
                "mode": "REPEATED",
                "name": "weightedBackendServices",
                "type": "RECORD"
              },
              {
                "fields": [
                  {
                    "mode": "NULLABLE",
                    "name": "backendService",
                    "type": "STRING"
                  },
                  {
                    "mode": "NULLABLE",
                    "name": "weight",
                    "type": "INTEGER"
                  },
                  {
                    "fields": [
                      {
                        "mode": "REPEATED",
                        "name": "requestHeadersToRemove",
                        "type": "STRING"
                      },
                      {
                        "fields": [
                          {
                            "mode": "NULLABLE",
                            "name": "headerName",
                            "type": "STRING"
                          },
                          {
                            "mode": "NULLABLE",
                            "name": "headerValue",
                            "type": "STRING"
                          },
                          {
                            "mode": "NULLABLE",
                            "name": "replace",
                            "type": "BOOLEAN"
                          }
                        ],
                        "mode": "REPEATED",
                        "name": "requestHeadersToAdd",
                        "type": "RECORD"
                      },
                      {
                        "mode": "REPEATED",
                        "name": "responseHeadersToRemove",
                        "type": "STRING"
                      },
                      {
                        "fields": [
                          {
                            "mode": "NULLABLE",
                            "name": "headerName",
                            "type": "STRING"
                          },
                          {
                            "mode": "NULLABLE",
                            "name": "headerValue",
                            "type": "STRING"
                          },
                          {
                            "mode": "NULLABLE",
                            "name": "replace",
                            "type": "BOOLEAN"
                          }
                        ],
                        "mode": "REPEATED",
                        "name": "responseHeadersToAdd",
                        "type": "RECORD"
                      }
                    ],
                    "mode": "NULLABLE",
                    "name": "headerAction",
                    "type": "RECORD"
                  }
                ],
                "mode": "REPEATED",
                "name": "weightedBackendService",
                "type": "RECORD"
              },
              {
                "fields": [
                  {
                    "mode": "NULLABLE",
                    "name": "pathPrefixRewrite",
                    "type": "STRING"
                  },
                  {
                    "mode": "NULLABLE",
                    "name": "hostRewrite",
                    "type": "STRING"
                  },
                  {
                    "mode": "NULLABLE",
                    "name": "pathTemplateRewrite",
                    "type": "STRING"
                  }
                ],
                "mode": "NULLABLE",
                "name": "urlRewrite",
                "type": "RECORD"
              },
              {
                "fields": [
                  {
                    "mode": "NULLABLE",
                    "name": "seconds",
                    "type": "STRING"
                  },
                  {
                    "mode": "NULLABLE",
                    "name": "nanos",
                    "type": "INTEGER"
                  }
                ],
                "mode": "NULLABLE",
                "name": "timeout",
                "type": "RECORD"
              },
              {
                "fields": [
                  {
                    "mode": "REPEATED",
                    "name": "retryConditions",
                    "type": "STRING"
                  },
                  {
                    "mode": "REPEATED",
                    "name": "retryCondition",
                    "type": "STRING"
                  },
                  {
                    "mode": "NULLABLE",
                    "name": "numRetries",
                    "type": "INTEGER"
                  },
                  {
                    "fields": [
                      {
                        "mode": "NULLABLE",
                        "name": "seconds",
                        "type": "STRING"
                      },
                      {
                        "mode": "NULLABLE",
                        "name": "nanos",
                        "type": "INTEGER"
                      }
                    ],
                    "mode": "NULLABLE",
                    "name": "perTryTimeout",
                    "type": "RECORD"
                  }
                ],
                "mode": "NULLABLE",
                "name": "retryPolicy",
                "type": "RECORD"
              },
              {
                "fields": [
                  {
                    "mode": "NULLABLE",
                    "name": "backendService",
                    "type": "STRING"
                  }
                ],
                "mode": "NULLABLE",
                "name": "requestMirrorPolicy",
                "type": "RECORD"
              },
              {
                "fields": [
                  {
                    "mode": "REPEATED",
                    "name": "allowOrigins",
                    "type": "STRING"
                  },
                  {
                    "mode": "REPEATED",
                    "name": "allowOrigin",
                    "type": "STRING"
                  },
                  {
                    "mode": "REPEATED",
                    "name": "allowOriginRegexes",
                    "type": "STRING"
                  },
                  {
                    "mode": "REPEATED",
                    "name": "allowOriginRegex",
                    "type": "STRING"
                  },
                  {
                    "mode": "REPEATED",
                    "name": "allowMethods",
                    "type": "STRING"
                  },
                  {
                    "mode": "REPEATED",
                    "name": "allowMethod",
                    "type": "STRING"
                  },
                  {
                    "mode": "REPEATED",
                    "name": "allowHeaders",
                    "type": "STRING"
                  },
                  {
                    "mode": "REPEATED",
                    "name": "allowHeader",
                    "type": "STRING"
                  },
                  {
                    "mode": "REPEATED",
                    "name": "exposeHeaders",
                    "type": "STRING"
                  },
                  {
                    "mode": "REPEATED",
                    "name": "exposeHeader",
                    "type": "STRING"
                  },
                  {
                    "mode": "NULLABLE",
                    "name": "maxAge",
                    "type": "INTEGER"
                  },
                  {
                    "mode": "NULLABLE",
                    "name": "allowCredentials",
                    "type": "BOOLEAN"
                  },
                  {
                    "mode": "NULLABLE",
                    "name": "disabled",
                    "type": "BOOLEAN"
                  }
                ],
                "mode": "NULLABLE",
                "name": "corsPolicy",
                "type": "RECORD"
              },
              {
                "fields": [
                  {
                    "fields": [
                      {
                        "fields": [
                          {
                            "mode": "NULLABLE",
                            "name": "seconds",
                            "type": "STRING"
                          },
                          {
                            "mode": "NULLABLE",
                            "name": "nanos",
                            "type": "INTEGER"
                          }
                        ],
                        "mode": "NULLABLE",
                        "name": "fixedDelay",
                        "type": "RECORD"
                      },
                      {
                        "mode": "NULLABLE",
                        "name": "percentage",
                        "type": "FLOAT"
                      }
                    ],
                    "mode": "NULLABLE",
                    "name": "delay",
                    "type": "RECORD"
                  },
                  {
                    "fields": [
                      {
                        "mode": "NULLABLE",
                        "name": "httpStatus",
                        "type": "INTEGER"
                      },
                      {
                        "mode": "NULLABLE",
                        "name": "percentage",
                        "type": "FLOAT"
                      }
                    ],
                    "mode": "NULLABLE",
                    "name": "abort",
                    "type": "RECORD"
                  }
                ],
                "mode": "NULLABLE",
                "name": "faultInjectionPolicy",
                "type": "RECORD"
              },
              {
                "fields": [
                  {
                    "mode": "NULLABLE",
                    "name": "seconds",
                    "type": "STRING"
                  },
                  {
                    "mode": "NULLABLE",
                    "name": "nanos",
                    "type": "INTEGER"
                  }
                ],
                "mode": "NULLABLE",
                "name": "maxStreamDuration",
                "type": "RECORD"
              }
            ],
            "mode": "NULLABLE",
            "name": "defaultRouteAction",
            "type": "RECORD"
          },
          {
            "fields": [
              {
                "mode": "NULLABLE",
                "name": "hostRedirect",
                "type": "STRING"
              },
              {
                "mode": "NULLABLE",
                "name": "pathRedirect",
                "type": "STRING"
              },
              {
                "mode": "NULLABLE",
                "name": "prefixRedirect",
                "type": "STRING"
              },
              {
                "mode": "NULLABLE",
                "name": "redirectResponseCode",
                "type": "STRING"
              },
              {
                "mode": "NULLABLE",
                "name": "httpsRedirect",
                "type": "BOOLEAN"
              },
              {
                "mode": "NULLABLE",
                "name": "stripQuery",
                "type": "BOOLEAN"
              }
            ],
            "mode": "NULLABLE",
            "name": "defaultUrlRedirect",
            "type": "RECORD"
          },
          {
            "fields": [
              {
                "mode": "REPEATED",
                "name": "requestHeadersToRemove",
                "type": "STRING"
              },
              {
                "fields": [
                  {
                    "mode": "NULLABLE",
                    "name": "headerName",
                    "type": "STRING"
                  },
                  {
                    "mode": "NULLABLE",
                    "name": "headerValue",
                    "type": "STRING"
                  },
                  {
                    "mode": "NULLABLE",
                    "name": "replace",
                    "type": "BOOLEAN"
                  }
                ],
                "mode": "REPEATED",
                "name": "requestHeadersToAdd",
                "type": "RECORD"
              },
              {
                "mode": "REPEATED",
                "name": "responseHeadersToRemove",
                "type": "STRING"
              },
              {
                "fields": [
                  {
                    "mode": "NULLABLE",
                    "name": "headerName",
                    "type": "STRING"
                  },
                  {
                    "mode": "NULLABLE",
                    "name": "headerValue",
                    "type": "STRING"
                  },
                  {
                    "mode": "NULLABLE",
                    "name": "replace",
                    "type": "BOOLEAN"
                  }
                ],
                "mode": "REPEATED",
                "name": "responseHeadersToAdd",
                "type": "RECORD"
              }
            ],
            "mode": "NULLABLE",
            "name": "headerAction",
            "type": "RECORD"
          },
          {
            "fields": [
              {
                "mode": "NULLABLE",
                "name": "errorService",
                "type": "STRING"
              }
            ],
            "mode": "NULLABLE",
            "name": "defaultCustomErrorResponsePolicy",
            "type": "RECORD"
          },
          {
            "mode": "NULLABLE",
            "name": "fingerprint",
            "type": "STRING"
          },
          {
            "mode": "NULLABLE",
            "name": "region",
            "type": "STRING"
          }
        ],
        "mode": "NULLABLE",
        "name": "data",
        "type": "RECORD"
      },
      {
        "mode": "NULLABLE",
        "name": "location",
        "type": "STRING"
      }
    ],
    "mode": "NULLABLE",
    "name": "resource",
    "type": "RECORD"
  },
  {
    "mode": "REPEATED",
    "name": "ancestors",
    "type": "STRING"
  },
  {
    "mode": "NULLABLE",
    "name": "updateTime",
    "type": "TIMESTAMP"
  }
]
